pyles.libs/libpcre-9513aab5.so.1.2.0
pyles.libs/libkrb5support-ec2f3e99.so.0.1
pyles.libs/libczmq-92ad04c1.so.4.2.0
pyles.libs/libz-d8a329de.so.1.2.7
pyles.libs/libteles-261b41b5.so.1.2.0
pyles.libs/libzmq-6d47fddd.so.5.0.0
pyles.libs/libuuid-506df98b.so.1.3.0
pyles.libs/libpgm-5-65caec62.2.so.0.0.122
pyles.libs/libk5crypto-d17c94d0.so.3.1
pyles.libs/libselinux-0922c95c.so.1
pyles.libs/libkrb5-0926b880.so.3.3
pyles.libs/libkeyutils-dfe70bd6.so.1.5
pyles.libs/libcom_err-64b66bbd.so.2.1
pyles.libs/libuv-fd8718f8.so.1.0.0
pyles.libs/libprotobuf-4f32d2e5.so.17.0.0
pyles.libs/libboost_program_options-cb7743a9.so.1.69.0
pyles.libs/libgssapi_krb5-0f360511.so.2.2
pyles.libs/libcfitsio-16f89096.so.2.3.37
pyles.libs/libsodium-7b30804c.so.23.3.0
pyles/__init__.py
pyles/_C.cpython-37m-x86_64-linux-gnu.so
pyles/logger.py
pyles/telesapp.py
pyles/proto/command_pb2.py
pyles/proto/property_pb2.py
pyles/proto/__init__.py
pyles/proto/info_pb2.py
pyles/proto/log_pb2.py
pyles-1.2.34.dist-info/top_level.txt
pyles-1.2.34.dist-info/METADATA
pyles-1.2.34.dist-info/RECORD
pyles-1.2.34.dist-info/WHEEL
