Metadata-Version: 2.1
Name: pyles
Version: 1.2.34
Summary: Python binding for teles
Home-page: UNKNOWN
Author: Guangyu Zhang
Author-email: zguangyu123@gmail.com
License: UNKNOWN
Platform: UNKNOWN
